mixpanel_api/__init__.py
mixpanel_api/dataset_load_example.py
mixpanel_api/datasets_examples.py
mixpanel_api/mixpanel_api_example.py
mixpanel_api/paginator.py
mixpanel_api3-0.2.1.dist-info/METADATA
mixpanel_api3-0.2.1.dist-info/RECORD
mixpanel_api3-0.2.1.dist-info/WHEEL
mixpanel_api3-0.2.1.dist-info/top_level.txt
