Metadata-Version: 1.1
Name: mixpanel-api3
Version: 0.2.1
Summary: Python3 Version of mixpanel-api. A utilities-only module for exporting and importing data into Mixpanel via their APIs. This is NOT for server-side app tracking.
Home-page: https://github.com/aavnsh/mixpanel_api3
Author: Avinash Anand
Author-email: asy8uo81p3g4@abinemail.com
License: UNKNOWN
Keywords: mixpanel,utilities,python3
Platform: UNKNOWN
Classifier: Development Status :: 4 - Beta
Classifier: Intended Audience :: Developers
Classifier: Programming Language :: Python :: 3
Classifier: Programming Language :: Python :: 3.6
Classifier: Topic :: Software Development :: Libraries :: Python Modules
Classifier: Topic :: Utilities
